.gitattributes
.gitignore
LICENSE.md
README.md
mkdocs.yml
pyproject.toml
uv.lock
.github/codecov.yaml
.github/workflows/ci.yaml
.github/workflows/pages.yaml
.github/workflows/release.yaml
docs/api_reference.md
docs/index.md
docs/assets/enve.png
docs/assets/logo.svg
src/enve/__init__.py
src/enve/_version.py
src/enve/cli.py
src/enve/parser.py
src/enve/py.typed
src/enve.egg-info/PKG-INFO
src/enve.egg-info/SOURCES.txt
src/enve.egg-info/dependency_links.txt
src/enve.egg-info/entry_points.txt
src/enve.egg-info/top_level.txt
tests/__init__.py
tests/cli_test.py
tests/parser_test.py
tests/sentinel_test.py
tests/typing_test.py
tests/version_test.py