Metadata-Version: 2.4
Name: enve
Version: 0.2.0
Summary: An environment variable parser library with type hint and conversion support.
Author-email: Aurélien Chick <aurelien.chick@gmail.com>
License-Expression: MIT
Project-URL: Homepage, https://github.com/aachick/enve
Project-URL: Documentation, https://aachick.github.io/enve
Project-URL: Repository, https://github.com/aachick/enve
Project-URL: Issues, https://github.com/aachick/enve/issues
Keywords: env,environment,environment variables
Classifier: Development Status :: 3 - Alpha
Classifier: Intended Audience :: Developers
Classifier: Intended Audience :: System Administrators
Classifier: Operating System :: OS Independent
Classifier: Programming Language :: Python :: 3.10
Classifier: Programming Language :: Python :: 3.11
Classifier: Programming Language :: Python :: 3.12
Classifier: Programming Language :: Python :: 3.13
Classifier: Topic :: System :: Systems Administration
Classifier: Topic :: Utilities
Classifier: Typing :: Typed
Requires-Python: >=3.10
License-File: LICENSE.md
Dynamic: license-file
